[{"text": "open my music and play melissas afternoon podcast from yesterday", "label": 50, "scenario": "play"}, {"text": "play yesterday's hot ninety seven morning show", "label": 50, "scenario": "play"}, {"text": "play my station", "label": 50, "scenario": "play"}, {"text": "play for me the music by the beatles", "label": 48, "scenario": "play"}, {"text": "hey olly play the radio", "label": 50, "scenario": "play"}, {"text": "play some music from metal genre", "label": 48, "scenario": "play"}, {"text": "play prairie home companion on the car radio", "label": 50, "scenario": "play"}, {"text": "play favourite music", "label": 48, "scenario": "play"}, {"text": "play the kansas city hip hop station", "label": 50, "scenario": "play"}, {"text": "play soundcloud", "label": 50, "scenario": "play"}, {"text": "play some tunes", "label": 48, "scenario": "play"}, {"text": "play bhuli bisri yaadien program on ninety one point three fm", "label": 50, "scenario": "play"}, {"text": "play my most played playlist", "label": 48, "scenario": "play"}, {"text": "play the sports station", "label": 50, "scenario": "play"}, {"text": "play all songs from playlist favorite", "label": 48, "scenario": "play"}, {"text": "on radio mirch can you play feel dil programme", "label": 50, "scenario": "play"}, {"text": "play the urban radio station", "label": 50, "scenario": "play"}, {"text": "play nine hundred and eighty nine the radio station", "label": 50, "scenario": "play"}, {"text": "shuffle and play blue playlist", "label": 48, "scenario": "play"}, {"text": "play the beatles", "label": 48, "scenario": "play"}, {"text": "play today song from radio seven", "label": 50, "scenario": "play"}, {"text": "play me all jazz music", "label": 48, "scenario": "play"}, {"text": "i'dl like to hear any classical except for bach or schubert", "label": 48, "scenario": "play"}, {"text": "play something from recent playlist", "label": 48, "scenario": "play"}, {"text": "open spotify and play personal channel", "label": 50, "scenario": "play"}, {"text": "i would like to listen to some rap music right now", "label": 48, "scenario": "play"}, {"text": "play bbc radio four please", "label": 50, "scenario": "play"}, {"text": "play techno music", "label": 48, "scenario": "play"}, {"text": "what are todays country hits", "label": 48, "scenario": "play"}, {"text": "play the radio for me", "label": 50, "scenario": "play"}, {"text": "play sixty", "label": 48, "scenario": "play"}, {"text": "play hot ninety seven radio", "label": 50, "scenario": "play"}, {"text": "play my itunes music", "label": 48, "scenario": "play"}, {"text": "play me this years top ten ten pop songs", "label": 48, "scenario": "play"}, {"text": "play lady by kenny rogers now", "label": 48, "scenario": "play"}, {"text": "play today song from radio seven", "label": 50, "scenario": "play"}, {"text": "play lite music in one oh six point seven", "label": 50, "scenario": "play"}, {"text": "can you play the instrumentals of", "label": 48, "scenario": "play"}, {"text": "i want to hear play that funky music", "label": 48, "scenario": "play"}, {"text": "play indi song from fm", "label": 50, "scenario": "play"}, {"text": "play me news radio channel", "label": 50, "scenario": "play"}, {"text": "play yesterday's hot ninety seven morning show", "label": 50, "scenario": "play"}, {"text": "play some calming music for me", "label": 48, "scenario": "play"}, {"text": "play this program", "label": 50, "scenario": "play"}, {"text": "please play some jazz", "label": 48, "scenario": "play"}, {"text": "play hot ninety seven radio", "label": 50, "scenario": "play"}, {"text": "play me a song by van halen", "label": 48, "scenario": "play"}, {"text": "let's play hits on the radio", "label": 50, "scenario": "play"}, {"text": "let me listen to my top rock songs playlist", "label": 48, "scenario": "play"}, {"text": "play bbc radio", "label": 50, "scenario": "play"}, {"text": "i want to hear i got you babe by sonny and cher can you play that", "label": 48, "scenario": "play"}, {"text": "play the radio please", "label": 50, "scenario": "play"}, {"text": "play for me ninety nine point five radio fm", "label": 50, "scenario": "play"}, {"text": "play for me american idol on television", "label": 50, "scenario": "play"}, {"text": "play december holiday list", "label": 48, "scenario": "play"}, {"text": "please play me something from the foo fighters", "label": 48, "scenario": "play"}, {"text": "play the most popular bluegrass music", "label": 48, "scenario": "play"}, {"text": "play queen", "label": 48, "scenario": "play"}, {"text": "let's dance", "label": 48, "scenario": "play"}, {"text": "play", "label": 50, "scenario": "play"}]