[{"text": "play me music", "label": 48, "scenario": "play"}, {"text": "could you play that radio channel", "label": 50, "scenario": "play"}, {"text": "i want to listen some music play a radio station", "label": 50, "scenario": "play"}, {"text": "play hip hop music", "label": 48, "scenario": "play"}, {"text": "play the song", "label": 48, "scenario": "play"}, {"text": "is there any birthday on june", "label": 7, "scenario": "calendar"}, {"text": "delete my birthday reminder for next week", "label": 8, "scenario": "calendar"}, {"text": "play rap", "label": 48, "scenario": "play"}, {"text": "play some radio", "label": 50, "scenario": "play"}, {"text": "do i have to do something later", "label": 7, "scenario": "calendar"}, {"text": "you are so helpful, musch appreciated.", "label": 26, "scenario": "general"}, {"text": "check on this week's weather report", "label": 67, "scenario": "weather"}, {"text": "title of song", "label": 43, "scenario": "music"}, {"text": "play some radio", "label": 50, "scenario": "play"}, {"text": "play this playlist", "label": 48, "scenario": "play"}, {"text": "please order one train ticket to los angeles", "label": 65, "scenario": "transport"}, {"text": "load a fun game that i can play with you", "label": 47, "scenario": "play"}, {"text": "do i have banana in my shopping list", "label": 39, "scenario": "lists"}, {"text": "play npr on the car radio", "label": 50, "scenario": "play"}, {"text": "play am", "label": 50, "scenario": "play"}, {"text": "play me some jazz", "label": 48, "scenario": "play"}, {"text": "play my favourite podcast", "label": 49, "scenario": "play"}, {"text": "i don't like this light please show me other options", "label": 31, "scenario": "iot"}, {"text": "play jazz", "label": 48, "scenario": "play"}, {"text": "let's play a game of chess", "label": 47, "scenario": "play"}, {"text": "this was not correct command.", "label": 25, "scenario": "general"}, {"text": "i hate this song do not play it again", "label": 41, "scenario": "music"}, {"text": "play cd led zeppelin houses of the holy", "label": 48, "scenario": "play"}, {"text": "please play the morning show on ninety one point five point one fm", "label": 50, "scenario": "play"}, {"text": "play music relating to the music i listened to this morning", "label": 48, "scenario": "play"}, {"text": "play jumper by third eye blind", "label": 48, "scenario": "play"}, {"text": "open the two towers and play", "label": 46, "scenario": "play"}, {"text": "where to buy cannon cameras", "label": 57, "scenario": "recommendation"}, {"text": "lets play pinball", "label": 47, "scenario": "play"}, {"text": "play the podcast", "label": 49, "scenario": "play"}, {"text": "good afternoon", "label": 23, "scenario": "general"}, {"text": "play song by daddy yankee", "label": 48, "scenario": "play"}, {"text": "play the latest seahawks podcast", "label": 49, "scenario": "play"}, {"text": "play the latest songs by dalida", "label": 48, "scenario": "play"}, {"text": "play classical music playlist", "label": 48, "scenario": "play"}, {"text": "play a r rahman music", "label": 48, "scenario": "play"}, {"text": "i was not clear about what you just said now.", "label": 22, "scenario": "general"}, {"text": "can i play golf in afternoon tomorrow", "label": 67, "scenario": "weather"}, {"text": "my calendar is to be updated with all rccg event in march", "label": 9, "scenario": "calendar"}, {"text": "play episode ten in the podcast", "label": 49, "scenario": "play"}, {"text": "mute all responses now", "label": 4, "scenario": "audio"}, {"text": "resume play of american gods", "label": 46, "scenario": "play"}, {"text": "play american idol for me now", "label": 50, "scenario": "play"}, {"text": "play my best song", "label": 48, "scenario": "play"}, {"text": "start the i'm feeling lucky playlist on google play", "label": 48, "scenario": "play"}, {"text": "look for this playback in audiobook and play for me", "label": 46, "scenario": "play"}, {"text": "play the second song from anirudh's song", "label": 48, "scenario": "play"}, {"text": "find restaurants within one miles", "label": 57, "scenario": "recommendation"}, {"text": "find a recipe for dinner tonight", "label": 11, "scenario": "cooking"}, {"text": "play madonnas like a virgin", "label": 48, "scenario": "play"}, {"text": "play real racing three game", "label": 47, "scenario": "play"}, {"text": "play last misesorg podcast", "label": 49, "scenario": "play"}, {"text": "play the neal brennan episode of wait wait don't tell me", "label": 50, "scenario": "play"}, {"text": "uh no, i think not correct response.", "label": 25, "scenario": "general"}, {"text": "play comedy from any fm channel", "label": 50, "scenario": "play"}, {"text": "play me news radio channel", "label": 50, "scenario": "play"}, {"text": "make an alarm to wake me up after five hours", "label": 2, "scenario": "alarm"}, {"text": "please play bbc radio station", "label": 50, "scenario": "play"}, {"text": "next play selected song", "label": 48, "scenario": "play"}, {"text": "please play me songs from the eighties", "label": 48, "scenario": "play"}, {"text": "play for me the album by the beatles on television", "label": 50, "scenario": "play"}, {"text": "play for me ninety nine point five radio fm", "label": 50, "scenario": "play"}, {"text": "show me the events in my work calendar for next week", "label": 9, "scenario": "calendar"}, {"text": "how is the traffic in florida", "label": 66, "scenario": "transport"}, {"text": "play the song from last night at six pm", "label": 48, "scenario": "play"}, {"text": "please tell me what time is now in canada", "label": 13, "scenario": "datetime"}, {"text": "play my favorite music right now", "label": 48, "scenario": "play"}, {"text": "play twenty questions", "label": 27, "scenario": "general"}, {"text": "play classical channel in sirius", "label": 50, "scenario": "play"}, {"text": "what's the weather supposed to be like on wednesday", "label": 67, "scenario": "weather"}, {"text": "play music by that artist", "label": 48, "scenario": "play"}, {"text": "play kiss from a rose", "label": 48, "scenario": "play"}, {"text": "turn off the lights please", "label": 33, "scenario": "iot"}, {"text": "which rom com movie can i watch in theatres around new york", "label": 58, "scenario": "recommendation"}, {"text": "what's the latest news from cnn please", "label": 45, "scenario": "news"}, {"text": "play netflix on my ps four", "label": 50, "scenario": "play"}, {"text": "play ipl two thousand and seventeen", "label": 50, "scenario": "play"}, {"text": "would you please play aces high", "label": 48, "scenario": "play"}, {"text": "please play some lady gaga", "label": 48, "scenario": "play"}, {"text": "can you play call me by aretha franklin after this song is finished playing", "label": 48, "scenario": "play"}, {"text": "play the weekend", "label": 48, "scenario": "play"}, {"text": "could you please play the classical music for me", "label": 48, "scenario": "play"}, {"text": "play queen", "label": 48, "scenario": "play"}, {"text": "what the conversion rate from yen to us dollars", "label": 51, "scenario": "qa"}, {"text": "play the urban radio station", "label": 50, "scenario": "play"}, {"text": "play news in fm", "label": 50, "scenario": "play"}, {"text": "play all order of the green hand from previous week", "label": 49, "scenario": "play"}, {"text": "let's play my song", "label": 48, "scenario": "play"}, {"text": "hello beef up the volume a little bit", "label": 6, "scenario": "audio"}, {"text": "play rohan sharma podcast for me", "label": 49, "scenario": "play"}, {"text": "play netflix on my ps four", "label": 50, "scenario": "play"}, {"text": "any funny jokes", "label": 24, "scenario": "general"}, {"text": "turn living room lights red", "label": 31, "scenario": "iot"}, {"text": "play song from my trance list", "label": 48, "scenario": "play"}, {"text": "play edms", "label": 48, "scenario": "play"}, {"text": "play nine hundred and seventy one", "label": 50, "scenario": "play"}, {"text": "play cnn radio", "label": 50, "scenario": "play"}, {"text": "play me john's podcast", "label": 49, "scenario": "play"}, {"text": "six am", "label": 9, "scenario": "calendar"}, {"text": "play random radio station", "label": 50, "scenario": "play"}, {"text": "are you sure that is the right command.", "label": 25, "scenario": "general"}, {"text": "play rock", "label": 48, "scenario": "play"}, {"text": "play some old school rap", "label": 48, "scenario": "play"}, {"text": "book train best deal", "label": 65, "scenario": "transport"}, {"text": "play me a random song", "label": 48, "scenario": "play"}, {"text": "play the podcast of barack obama saved in device", "label": 49, "scenario": "play"}, {"text": "i like justin beibers music please play it", "label": 42, "scenario": "music"}, {"text": "play some rock music", "label": 48, "scenario": "play"}, {"text": "in the calendar put that we are having dinner with frank at eight pm on the ninth of august", "label": 9, "scenario": "calendar"}, {"text": "play all by the beatles", "label": 48, "scenario": "play"}, {"text": "hello google play baby one more time", "label": 48, "scenario": "play"}, {"text": "play me some music", "label": 48, "scenario": "play"}, {"text": "play the playlist we were listening last night", "label": 48, "scenario": "play"}, {"text": "is my order ready for pick up now", "label": 62, "scenario": "takeaway"}, {"text": "should i wear sunblock today", "label": 67, "scenario": "weather"}, {"text": "play for me the game cricket", "label": 47, "scenario": "play"}, {"text": "play dinner party music", "label": 48, "scenario": "play"}, {"text": "clear up my calendar", "label": 8, "scenario": "calendar"}, {"text": "play me some jazz", "label": 48, "scenario": "play"}, {"text": "can you play songs about breakups", "label": 48, "scenario": "play"}, {"text": "just play nine hundred and thirty seven fm", "label": 50, "scenario": "play"}, {"text": "play bbc radio four", "label": 50, "scenario": "play"}, {"text": "how old is cher", "label": 53, "scenario": "qa"}, {"text": "resume audiobook player", "label": 46, "scenario": "play"}, {"text": "play me my favourite radio show", "label": 50, "scenario": "play"}, {"text": "open podcasts and play my favorites list", "label": 49, "scenario": "play"}, {"text": "please play thriller", "label": 48, "scenario": "play"}, {"text": "play spotify playlist blank", "label": 48, "scenario": "play"}, {"text": "inform about latest scheduled events near my location", "label": 56, "scenario": "recommendation"}, {"text": "could you speak that once more.", "label": 28, "scenario": "general"}, {"text": "could you please play the fm station which plays pop songs", "label": 50, "scenario": "play"}, {"text": "play nine hundred and forty five fm", "label": 50, "scenario": "play"}, {"text": "can you play my favorite audio book of tarzan", "label": 46, "scenario": "play"}, {"text": "play the next episode of a podcast", "label": 49, "scenario": "play"}, {"text": "schedule", "label": 7, "scenario": "calendar"}, {"text": "play a podcast about dogs", "label": 49, "scenario": "play"}, {"text": "what does my facebook feed look like", "label": 60, "scenario": "social"}, {"text": "play for me hip hop music", "label": 48, "scenario": "play"}, {"text": "play nine hundred and seventy one", "label": 50, "scenario": "play"}, {"text": "look out for customer complaint cell and use the options", "label": 59, "scenario": "social"}, {"text": "play led zeppelin houses of the holy", "label": 48, "scenario": "play"}, {"text": "play the sports station", "label": 50, "scenario": "play"}, {"text": "turn off lights", "label": 33, "scenario": "iot"}, {"text": "please remind me that i have a meeting tomorrow ten in the morning", "label": 9, "scenario": "calendar"}, {"text": "play songs by bryan adams", "label": 48, "scenario": "play"}]