[{"text": "hey olly play me an automated playlist based on songs heard in gaana app this week", "label": 48, "scenario": "play"}, {"text": "play music i have liked", "label": 48, "scenario": "play"}, {"text": "play am", "label": 50, "scenario": "play"}, {"text": "play national public radio", "label": 50, "scenario": "play"}, {"text": "please play thriller", "label": 48, "scenario": "play"}, {"text": "play the latest episode of little steven's underground garage", "label": 50, "scenario": "play"}, {"text": "play edms", "label": 48, "scenario": "play"}, {"text": "play radio one programme one", "label": 50, "scenario": "play"}, {"text": "play my recently downloaded songs", "label": 48, "scenario": "play"}, {"text": "music third day", "label": 48, "scenario": "play"}, {"text": "play my gym playlist", "label": 48, "scenario": "play"}, {"text": "play new radio channel", "label": 50, "scenario": "play"}, {"text": "play romantic english songs", "label": 48, "scenario": "play"}, {"text": "play new rihanna song", "label": 48, "scenario": "play"}, {"text": "start pandora and play the beatles", "label": 50, "scenario": "play"}, {"text": "play radio on five point thirty on tere nagme show", "label": 50, "scenario": "play"}, {"text": "play album", "label": 48, "scenario": "play"}, {"text": "nobody knows", "label": 48, "scenario": "play"}, {"text": "play songs by the band the beatles", "label": 48, "scenario": "play"}, {"text": "play me all jazz music", "label": 48, "scenario": "play"}, {"text": "play something with three or more stars from new music", "label": 48, "scenario": "play"}, {"text": "play song all the small things", "label": 48, "scenario": "play"}, {"text": "just play nine hundred and thirty seven fm", "label": 50, "scenario": "play"}, {"text": "play my itunes music", "label": 48, "scenario": "play"}, {"text": "play the song which is in movie rangoon", "label": 48, "scenario": "play"}, {"text": "open my music and play melissas afternoon podcast from yesterday", "label": 50, "scenario": "play"}, {"text": "go to youtube and play me the best wedding songs collection", "label": 48, "scenario": "play"}, {"text": "play a pop station on the radio", "label": 50, "scenario": "play"}, {"text": "open my music and play melissas afternoon podcast from yesterday", "label": 50, "scenario": "play"}, {"text": "play npr on this station", "label": 50, "scenario": "play"}, {"text": "play song aces high", "label": 48, "scenario": "play"}, {"text": "play song by daddy yankee", "label": 48, "scenario": "play"}, {"text": "play radio one", "label": 50, "scenario": "play"}, {"text": "open pandora and play hoizer radio", "label": 50, "scenario": "play"}, {"text": "play the rock ninety two radio channel", "label": 50, "scenario": "play"}, {"text": "play for me ninety nine point five radio fm", "label": 50, "scenario": "play"}, {"text": "open pandora and play workout", "label": 50, "scenario": "play"}, {"text": "play radio javan", "label": 50, "scenario": "play"}, {"text": "can you find the newest song from mgk", "label": 48, "scenario": "play"}, {"text": "play npr through my living room stereo", "label": 50, "scenario": "play"}, {"text": "play this american life on the kitchen radio", "label": 50, "scenario": "play"}, {"text": "play tunes", "label": 50, "scenario": "play"}, {"text": "make happy birthday the next song", "label": 48, "scenario": "play"}, {"text": "play radio mirchi for me", "label": 50, "scenario": "play"}, {"text": "turn on some npr and play them out of my speakers", "label": 50, "scenario": "play"}, {"text": "play lady by kenny rogers now", "label": 48, "scenario": "play"}, {"text": "play alex jones in radio", "label": 50, "scenario": "play"}, {"text": "open media player and play top hits", "label": 50, "scenario": "play"}, {"text": "play music from my favorite pianist", "label": 48, "scenario": "play"}, {"text": "play lite music in one oh six point seven", "label": 50, "scenario": "play"}, {"text": "play the radio for me", "label": 50, "scenario": "play"}, {"text": "music from the", "label": 48, "scenario": "play"}, {"text": "play some radio", "label": 50, "scenario": "play"}, {"text": "load sirius and play a rock and roll show", "label": 50, "scenario": "play"}, {"text": "can you play rock music for the next hour", "label": 48, "scenario": "play"}, {"text": "play lady by kenny roger", "label": 48, "scenario": "play"}, {"text": "play dr demento on my bedside radio", "label": 50, "scenario": "play"}, {"text": "after this song please play this song", "label": 48, "scenario": "play"}, {"text": "play a selection of classical music", "label": 48, "scenario": "play"}, {"text": "play songs by bryan adams", "label": 48, "scenario": "play"}]